pycryptofile/__init__.py
pycryptofile/pyCryptoFile.py
pycryptofile-1.0.8.dist-info/LICENSE.txt
pycryptofile-1.0.8.dist-info/METADATA
pycryptofile-1.0.8.dist-info/WHEEL
pycryptofile-1.0.8.dist-info/top_level.txt
pycryptofile-1.0.8.dist-info/RECORD
