Metadata-Version: 2.1
Name: pycryptofile
Version: 1.0.8
Summary: pycryptofile allows to encrypt/decrypt using ssh keys
Home-page: https://github.com/stormalf/file_transfer
Author: Stormalf
Author-email: stormalf.dev@gmail.com
License: UNKNOWN
Project-URL: Bug Reports, https://github.com/stormalf/file_transfer/issues
Project-URL: Source, https://github.com/stormalf/file_transfer/
Keywords: pycryptofile
Platform: UNKNOWN
Classifier: Development Status :: 3 - Alpha
Classifier: Intended Audience :: Developers
Classifier: Topic :: Software Development :: Build Tools
Classifier: License :: OSI Approved :: MIT License
Classifier: Programming Language :: Python :: 3
Classifier: Programming Language :: Python :: 3.6
Classifier: Programming Language :: Python :: 3.7
Classifier: Programming Language :: Python :: 3.8
Classifier: Programming Language :: Python :: 3.9
Classifier: Programming Language :: Python :: 3 :: Only
Requires-Python: >=3.6, <4
License-File: LICENSE.txt
Requires-Dist: pycrypto
Requires-Dist: setuptools (>=40.8.0)
Requires-Dist: wheel
Requires-Dist: argparse
